MANIFEST.in
README.rst
setup.py
polls/__init__.py
polls/admin.py
polls/apps.py
polls/models.py
polls/tests.py
polls/urls.py
polls/views.py
polls/migrations/0001_initial.py
polls/migrations/__init__.py
polls/static/polls/style.css
polls/static/polls/images/background.gif
polls/templates/polls/detail.html
polls/templates/polls/index.html
polls/templates/polls/results.html
wbs_polls_djn.egg-info/PKG-INFO
wbs_polls_djn.egg-info/SOURCES.txt
wbs_polls_djn.egg-info/dependency_links.txt
wbs_polls_djn.egg-info/top_level.txt